Workbook

Sheet Dashboard
A1: E-commerce FP&A Dashboard
A3: FY2026 Revenue | B3: =SUM(Model!B2:B13) | D3: Ending Cash | E3: =Model!P13
A4: FY2026 EBITDA | B4: =SUM(Model!K2:K13) | D4: Forecast Revenue (Jul-Dec) | E4: =SUM(Model!B8:B13)
A5: Average Gross Margin | B5: =AVERAGE(Model!F2:F13) | D5: Forecast EBITDA (Jul-Dec) | E5: =SUM(Model!K8:K13)
A6: Average EBITDA Margin | B6: =AVERAGE(Model!L2:L13) | D6: Cash Floor | E6: =MIN(Model!P2:P13)
A8: Key management questions
A9: 1. Is revenue growth translating into EBITDA growth?
A10: 2. What happens to cash if AR days increase?
A11: 3. Which assumptions most affect margin?
A12: 4. Where do actuals differ materially from forecast?

Sheet Model
A1: Month | B1: Revenue | C1: COGS % | D1: COGS | E1: Gross Profit | F1: Gross Margin % | G1: Marketing % | H1: Marketing | I1: Payroll | J1: Other OpEx | K1: EBITDA | L1: EBITDA Margin % | M1: AR Days | N1: AP Days | O1: Operating Cash Flow | P1: Ending Cash
A2: 46023 | B2: 118000 | C2: 0.41 | D2: =B2*C2 | E2: =B2-D2 | F2: =IFERROR(E2/B2,0) | G2: 0.14 | H2: =B2*G2 | I2: 21000 | J2: 8500 | K2: =E2-H2-I2-J2 | L2: =IFERROR(K2/B2,0) | M2: 35 | N2: 28 | O2: =K2-(B2/30*C2)+(D2/30*N2) | P2: =120000+O2
A3: 46054 | B3: 124000 | C3: 0.4 | D3: =B3*C3 | E3: =B3-D3 | F3: =IFERROR(E3/B3,0) | G3: 0.145 | H3: =B3*G3 | I3: 21200 | J3: 8600 | K3: =E3-H3-I3-J3 | L3: =IFERROR(K3/B3,0) | M3: 35 | N3: 28 | O3: =K3-(B3/30*C3)+(D3/30*N3) | P3: =P2+O3
A4: 46082 | B4: 132000 | C4: 0.405 | D4: =B4*C4 | E4: =B4-D4 | F4: =IFERROR(E4/B4,0) | G4: 0.15 | H4: =B4*G4 | I4: 21500 | J4: 8700 | K4: =E4-H4-I4-J4 | L4: =IFERROR(K4/B4,0) | M4: 35 | N4: 28 | O4: =K4-(B4/30*C4)+(D4/30*N4) | P4: =P3+O4
A5: 46113 | B5: 128000 | C5: 0.42 | D5: =B5*C5 | E5: =B5-D5 | F5: =IFERROR(E5/B5,0) | G5: 0.148 | H5: =B5*G5 | I5: 21800 | J5: 8800 | K5: =E5-H5-I5-J5 | L5: =IFERROR(K5/B5,0) | M5: 35 | N5: 28 | O5: =K5-(B5/30*C5)+(D5/30*N5) | P5: =P4+O5
A6: 46143 | B6: 141000 | C6: 0.395 | D6: =B6*C6 | E6: =B6-D6 | F6: =IFERROR(E6/B6,0) | G6: 0.15 | H6: =B6*G6 | I6: 22000 | J6: 9000 | K6: =E6-H6-I6-J6 | L6: =IFERROR(K6/B6,0) | M6: 35 | N6: 28 | O6: =K6-(B6/30*C6)+(D6/30*N6) | P6: =P5+O6
A7: 46174 | B7: 149000 | C7: 0.39 | D7: =B7*C7 | E7: =B7-D7 | F7: =IFERROR(E7/B7,0) | G7: 0.152 | H7: =B7*G7 | I7: 22500 | J7: 9200 | K7: =E7-H7-I7-J7 | L7: =IFERROR(K7/B7,0) | M7: 35 | N7: 28 | O7: =K7-(B7/30*C7)+(D7/30*N7) | P7: =P6+O7
A8: 46204 | B8: 155000 | C8: 0.385 | D8: =B8*C8 | E8: =B8-D8 | F8: =IFERROR(E8/B8,0) | G8: 0.15 | H8: =B8*G8 | I8: 23000 | J8: 9400 | K8: =E8-H8-I8-J8 | L8: =IFERROR(K8/B8,0) | M8: 35 | N8: 28 | O8: =K8-(B8/30*C8)+(D8/30*N8) | P8: =P7+O8
A9: 46235 | B9: 162000 | C9: 0.38 | D9: =B9*C9 | E9: =B9-D9 | F9: =IFERROR(E9/B9,0) | G9: 0.148 | H9: =B9*G9 | I9: 23500 | J9: 9600 | K9: =E9-H9-I9-J9 | L9: =IFERROR(K9/B9,0) | M9: 35 | N9: 28 | O9: =K9-(B9/30*C9)+(D9/30*N9) | P9: =P8+O9
A10: 46266 | B10: 170000 | C10: 0.38 | D10: =B10*C10 | E10: =B10-D10 | F10: =IFERROR(E10/B10,0) | G10: 0.145 | H10: =B10*G10 | I10: 24000 | J10: 9800 | K10: =E10-H10-I10-J10 | L10: =IFERROR(K10/B10,0) | M10: 35 | N10: 28 | O10: =K10-(B10/30*C10)+(D10/30*N10) | P10: =P9+O10
A11: 46296 | B11: 178000 | C11: 0.375 | D11: =B11*C11 | E11: =B11-D11 | F11: =IFERROR(E11/B11,0) | G11: 0.143 | H11: =B11*G11 | I11: 24500 | J11: 10000 | K11: =E11-H11-I11-J11 | L11: =IFERROR(K11/B11,0) | M11: 35 | N11: 28 | O11: =K11-(B11/30*C11)+(D11/30*N11) | P11: =P10+O11
A12: 46327 | B12: 187000 | C12: 0.37 | D12: =B12*C12 | E12: =B12-D12 | F12: =IFERROR(E12/B12,0) | G12: 0.14 | H12: =B12*G12 | I12: 25000 | J12: 10200 | K12: =E12-H12-I12-J12 | L12: =IFERROR(K12/B12,0) | M12: 35 | N12: 28 | O12: =K12-(B12/30*C12)+(D12/30*N12) | P12: =P11+O12
A13: 46357 | B13: 196000 | C13: 0.37 | D13: =B13*C13 | E13: =B13-D13 | F13: =IFERROR(E13/B13,0) | G13: 0.14 | H13: =B13*G13 | I13: 25500 | J13: 10400 | K13: =E13-H13-I13-J13 | L13: =IFERROR(K13/B13,0) | M13: 35 | N13: 28 | O13: =K13-(B13/30*C13)+(D13/30*N13) | P13: =P12+O13

Sheet Assumptions
A1: Assumption | B1: Base | C1: Downside | D1: Upside
A2: Revenue growth (forecast avg) | B2: 0.075 | C2: 0.03 | D2: 0.11
A3: COGS % | B3: 0.375 | C3: 0.41 | D3: 0.35
A4: Marketing % | B4: 0.14 | C4: 0.17 | D4: 0.12
A5: Payroll growth | B5: 0.04 | C5: 0.06 | D5: 0.03
A6: AR days | B6: 35 | C6: 45 | D6: 30
A7: AP days | B7: 28 | C7: 21 | D7: 35

Sheet Scenarios
A1: Month | B1: Base Revenue | C1: Downside Revenue | D1: Upside Revenue | E1: Base EBITDA | F1: Downside EBITDA | G1: Upside EBITDA
A2: 46023 | B2: 118000 | C2: 118000 | D2: 118000 | E2: =B2*(1-Assumptions!$B$3-Assumptions!$B$4)-Model!I2-Model!J2 | F2: =C2*(1-Assumptions!$C$3-Assumptions!$C$4)-Model!I2*(1+Assumptions!$C$5)-Model!J2 | G2: =D2*(1-Assumptions!$D$3-Assumptions!$D$4)-Model!I2*(1+Assumptions!$D$5)-Model!J2
A3: 46054 | B3: 124000 | C3: 124000 | D3: 124000 | E3: =B3*(1-Assumptions!$B$3-Assumptions!$B$4)-Model!I3-Model!J3 | F3: =C3*(1-Assumptions!$C$3-Assumptions!$C$4)-Model!I3*(1+Assumptions!$C$5)-Model!J3 | G3: =D3*(1-Assumptions!$D$3-Assumptions!$D$4)-Model!I3*(1+Assumptions!$D$5)-Model!J3
A4: 46082 | B4: 132000 | C4: 132000 | D4: 132000 | E4: =B4*(1-Assumptions!$B$3-Assumptions!$B$4)-Model!I4-Model!J4 | F4: =C4*(1-Assumptions!$C$3-Assumptions!$C$4)-Model!I4*(1+Assumptions!$C$5)-Model!J4 | G4: =D4*(1-Assumptions!$D$3-Assumptions!$D$4)-Model!I4*(1+Assumptions!$D$5)-Model!J4
A5: 46113 | B5: 128000 | C5: 128000 | D5: 128000 | E5: =B5*(1-Assumptions!$B$3-Assumptions!$B$4)-Model!I5-Model!J5 | F5: =C5*(1-Assumptions!$C$3-Assumptions!$C$4)-Model!I5*(1+Assumptions!$C$5)-Model!J5 | G5: =D5*(1-Assumptions!$D$3-Assumptions!$D$4)-Model!I5*(1+Assumptions!$D$5)-Model!J5
A6: 46143 | B6: 141000 | C6: 141000 | D6: 141000 | E6: =B6*(1-Assumptions!$B$3-Assumptions!$B$4)-Model!I6-Model!J6 | F6: =C6*(1-Assumptions!$C$3-Assumptions!$C$4)-Model!I6*(1+Assumptions!$C$5)-Model!J6 | G6: =D6*(1-Assumptions!$D$3-Assumptions!$D$4)-Model!I6*(1+Assumptions!$D$5)-Model!J6
A7: 46174 | B7: 149000 | C7: 149000 | D7: 149000 | E7: =B7*(1-Assumptions!$B$3-Assumptions!$B$4)-Model!I7-Model!J7 | F7: =C7*(1-Assumptions!$C$3-Assumptions!$C$4)-Model!I7*(1+Assumptions!$C$5)-Model!J7 | G7: =D7*(1-Assumptions!$D$3-Assumptions!$D$4)-Model!I7*(1+Assumptions!$D$5)-Model!J7
A8: 46204 | B8: 160175 | C8: 152967.12 | D8: 165781.12 | E8: =B8*(1-Assumptions!$B$3-Assumptions!$B$4)-Model!I8-Model!J8 | F8: =C8*(1-Assumptions!$C$3-Assumptions!$C$4)-Model!I8*(1+Assumptions!$C$5)-Model!J8 | G8: =D8*(1-Assumptions!$D$3-Assumptions!$D$4)-Model!I8*(1+Assumptions!$D$5)-Model!J8
A9: 46235 | B9: 166625 | C9: 159126.88 | D9: 172456.88 | E9: =B9*(1-Assumptions!$B$3-Assumptions!$B$4)-Model!I9-Model!J9 | F9: =C9*(1-Assumptions!$C$3-Assumptions!$C$4)-Model!I9*(1+Assumptions!$C$5)-Model!J9 | G9: =D9*(1-Assumptions!$D$3-Assumptions!$D$4)-Model!I9*(1+Assumptions!$D$5)-Model!J9
A10: 46266 | B10: 174150 | C10: 166313.25 | D10: 180245.25 | E10: =B10*(1-Assumptions!$B$3-Assumptions!$B$4)-Model!I10-Model!J10 | F10: =C10*(1-Assumptions!$C$3-Assumptions!$C$4)-Model!I10*(1+Assumptions!$C$5)-Model!J10 | G10: =D10*(1-Assumptions!$D$3-Assumptions!$D$4)-Model!I10*(1+Assumptions!$D$5)-Model!J10
A11: 46296 | B11: 182750 | C11: 174526.25 | D11: 189146.25 | E11: =B11*(1-Assumptions!$B$3-Assumptions!$B$4)-Model!I11-Model!J11 | F11: =C11*(1-Assumptions!$C$3-Assumptions!$C$4)-Model!I11*(1+Assumptions!$C$5)-Model!J11 | G11: =D11*(1-Assumptions!$D$3-Assumptions!$D$4)-Model!I11*(1+Assumptions!$D$5)-Model!J11
A12: 46327 | B12: 191350 | C12: 182739.25 | D12: 198047.25 | E12: =B12*(1-Assumptions!$B$3-Assumptions!$B$4)-Model!I12-Model!J12 | F12: =C12*(1-Assumptions!$C$3-Assumptions!$C$4)-Model!I12*(1+Assumptions!$C$5)-Model!J12 | G12: =D12*(1-Assumptions!$D$3-Assumptions!$D$4)-Model!I12*(1+Assumptions!$D$5)-Model!J12
A13: 46357 | B13: 201025 | C13: 191978.88 | D13: 208060.88 | E13: =B13*(1-Assumptions!$B$3-Assumptions!$B$4)-Model!I13-Model!J13 | F13: =C13*(1-Assumptions!$C$3-Assumptions!$C$4)-Model!I13*(1+Assumptions!$C$5)-Model!J13 | G13: =D13*(1-Assumptions!$D$3-Assumptions!$D$4)-Model!I13*(1+Assumptions!$D$5)-Model!J13
