Workbook

Sheet Dashboard
A1: E-commerce FP&A Dashboard
A3: FY2026 Revenue | B3: =SUM(Model!B2:B13) -> 1840000 | D3: Ending Cash | E3: =Model!P13 -> 1232978
A4: FY2026 EBITDA | B4: =SUM(Model!K2:K13) -> 471008 | D4: Forecast Revenue (Jul-Dec) | E4: =SUM(Model!B8:B13) -> 1048000
A5: Average Gross Margin | B5: =AVERAGE(Model!F2:F13) -> 0.61 | D5: Forecast EBITDA (Jul-Dec) | E5: =SUM(Model!K8:K13) -> 297855
A6: Average EBITDA Margin | B6: =AVERAGE(Model!L2:L13) -> 0.25006847 | D6: Cash Floor | E6: =MIN(Model!P2:P13) -> 187142
A8: Key management questions
A9: 1. What is driving revenue and EBITDA growth?
A10: 2. Where are margins under pressure?
A11: 3. How sensitive is cash to working-capital assumptions?
A12: 4. What changes under downside/upside scenarios?

Sheet Model
A1: Month | B1: Revenue | C1: COGS % | D1: COGS | E1: Gross Profit | F1: Gross Margin % | G1: Marketing % | H1: Marketing | I1: Payroll | J1: Other OpEx | K1: EBITDA | L1: EBITDA Margin % | M1: AR Days | N1: AP Days | O1: Operating Cash Flow | P1: Ending Cash
A2: Jan-26 | B2: 118000 | C2: 0.41 | D2: =B2*C2 -> 48380 | E2: =B2-D2 -> 69620 | F2: =IFERROR(E2/B2,0) -> 0.59 | G2: 0.14 | H2: =B2*G2 -> 16520 | I2: 21000 | J2: 8500 | K2: =E2-H2-I2-J2 -> 23600 | L2: =IFERROR(K2/B2,0) -> 0.2 | M2: 35 | N2: 28 | O2: =K2-(B2/30*C2)+(D2/30*N2) -> 67142 | P2: =120000+O2 -> 187142
A3: Feb-26 | B3: 124000 | C3: 0.4 | D3: =B3*C3 -> 49600 | E3: =B3-D3 -> 74400 | F3: =IFERROR(E3/B3,0) -> 0.6 | G3: 0.145 | H3: =B3*G3 -> 17980 | I3: 21200 | J3: 8600 | K3: =E3-H3-I3-J3 -> 26620 | L3: =IFERROR(K3/B3,0) -> 0.21467742 | M3: 35 | N3: 28 | O3: =K3-(B3/30*C3)+(D3/30*N3) -> 71260 | P3: =P2+O3 -> 258402
A4: Mar-26 | B4: 132000 | C4: 0.405 | D4: =B4*C4 -> 53460 | E4: =B4-D4 -> 78540 | F4: =IFERROR(E4/B4,0) -> 0.595 | G4: 0.15 | H4: =B4*G4 -> 19800 | I4: 21500 | J4: 8700 | K4: =E4-H4-I4-J4 -> 28540 | L4: =IFERROR(K4/B4,0) -> 0.21621212 | M4: 35 | N4: 28 | O4: =K4-(B4/30*C4)+(D4/30*N4) -> 76654 | P4: =P3+O4 -> 335056
A5: Apr-26 | B5: 128000 | C5: 0.42 | D5: =B5*C5 -> 53760 | E5: =B5-D5 -> 74240 | F5: =IFERROR(E5/B5,0) -> 0.58 | G5: 0.148 | H5: =B5*G5 -> 18944 | I5: 21800 | J5: 8800 | K5: =E5-H5-I5-J5 -> 24696 | L5: =IFERROR(K5/B5,0) -> 0.1929375 | M5: 35 | N5: 28 | O5: =K5-(B5/30*C5)+(D5/30*N5) -> 73080 | P5: =P4+O5 -> 408136
A6: May-26 | B6: 141000 | C6: 0.395 | D6: =B6*C6 -> 55695 | E6: =B6-D6 -> 85305 | F6: =IFERROR(E6/B6,0) -> 0.605 | G6: 0.15 | H6: =B6*G6 -> 21150 | I6: 22000 | J6: 9000 | K6: =E6-H6-I6-J6 -> 33155 | L6: =IFERROR(K6/B6,0) -> 0.23514184 | M6: 35 | N6: 28 | O6: =K6-(B6/30*C6)+(D6/30*N6) -> 83280.5 | P6: =P5+O6 -> 491416.5
A7: Jun-26 | B7: 149000 | C7: 0.39 | D7: =B7*C7 -> 58110 | E7: =B7-D7 -> 90890 | F7: =IFERROR(E7/B7,0) -> 0.61 | G7: 0.152 | H7: =B7*G7 -> 22648 | I7: 22500 | J7: 9200 | K7: =E7-H7-I7-J7 -> 36542 | L7: =IFERROR(K7/B7,0) -> 0.24524832 | M7: 35 | N7: 28 | O7: =K7-(B7/30*C7)+(D7/30*N7) -> 88841 | P7: =P6+O7 -> 580257.5
A8: Jul-26 | B8: 155000 | C8: 0.385 | D8: =B8*C8 -> 59675 | E8: =B8-D8 -> 95325 | F8: =IFERROR(E8/B8,0) -> 0.615 | G8: 0.15 | H8: =B8*G8 -> 23250 | I8: 23000 | J8: 9400 | K8: =E8-H8-I8-J8 -> 39675 | L8: =IFERROR(K8/B8,0) -> 0.25596774 | M8: 35 | N8: 28 | O8: =K8-(B8/30*C8)+(D8/30*N8) -> 93382.5 | P8: =P7+O8 -> 673640
A9: Aug-26 | B9: 162000 | C9: 0.38 | D9: =B9*C9 -> 61560 | E9: =B9-D9 -> 100440 | F9: =IFERROR(E9/B9,0) -> 0.62 | G9: 0.148 | H9: =B9*G9 -> 23976 | I9: 23500 | J9: 9600 | K9: =E9-H9-I9-J9 -> 43364 | L9: =IFERROR(K9/B9,0) -> 0.26767901 | M9: 35 | N9: 28 | O9: =K9-(B9/30*C9)+(D9/30*N9) -> 98768 | P9: =P8+O9 -> 772408
A10: Sep-26 | B10: 170000 | C10: 0.38 | D10: =B10*C10 -> 64600 | E10: =B10-D10 -> 105400 | F10: =IFERROR(E10/B10,0) -> 0.62 | G10: 0.145 | H10: =B10*G10 -> 24650 | I10: 24000 | J10: 9800 | K10: =E10-H10-I10-J10 -> 46950 | L10: =IFERROR(K10/B10,0) -> 0.27617647 | M10: 35 | N10: 28 | O10: =K10-(B10/30*C10)+(D10/30*N10) -> 105090 | P10: =P9+O10 -> 877498
A11: Oct-26 | B11: 178000 | C11: 0.375 | D11: =B11*C11 -> 66750 | E11: =B11-D11 -> 111250 | F11: =IFERROR(E11/B11,0) -> 0.625 | G11: 0.143 | H11: =B11*G11 -> 25454 | I11: 24500 | J11: 10000 | K11: =E11-H11-I11-J11 -> 51296 | L11: =IFERROR(K11/B11,0) -> 0.28817978 | M11: 35 | N11: 28 | O11: =K11-(B11/30*C11)+(D11/30*N11) -> 111371 | P11: =P10+O11 -> 988869
A12: Nov-26 | B12: 187000 | C12: 0.37 | D12: =B12*C12 -> 69190 | E12: =B12-D12 -> 117810 | F12: =IFERROR(E12/B12,0) -> 0.63 | G12: 0.14 | H12: =B12*G12 -> 26180 | I12: 25000 | J12: 10200 | K12: =E12-H12-I12-J12 -> 56430 | L12: =IFERROR(K12/B12,0) -> 0.30176471 | M12: 35 | N12: 28 | O12: =K12-(B12/30*C12)+(D12/30*N12) -> 118701 | P12: =P11+O12 -> 1107570
A13: Dec-26 | B13: 196000 | C13: 0.37 | D13: =B13*C13 -> 72520 | E13: =B13-D13 -> 123480 | F13: =IFERROR(E13/B13,0) -> 0.63 | G13: 0.14 | H13: =B13*G13 -> 27440 | I13: 25500 | J13: 10400 | K13: =E13-H13-I13-J13 -> 60140 | L13: =IFERROR(K13/B13,0) -> 0.30683673 | M13: 35 | N13: 28 | O13: =K13-(B13/30*C13)+(D13/30*N13) -> 125408 | P13: =P12+O13 -> 1232978

Sheet Assumptions
A1: Assumption | B1: Base | C1: Downside | D1: Upside
A2: Revenue growth (forecast avg) | B2: 0.075 | C2: 0.03 | D2: 0.11
A3: COGS % | B3: 0.375 | C3: 0.41 | D3: 0.35
A4: Marketing % | B4: 0.14 | C4: 0.17 | D4: 0.12
A5: Payroll growth | B5: 0.04 | C5: 0.06 | D5: 0.03
A6: AR days | B6: 35 | C6: 45 | D6: 30
A7: AP days | B7: 28 | C7: 21 | D7: 35

Sheet Scenarios
A1: Month | B1: Base Revenue | C1: Downside Revenue | D1: Upside Revenue | E1: Base EBITDA | F1: Downside EBITDA | G1: Upside EBITDA
A2: Jan-26 | B2: =Model!B2 -> 118000 | C2: =Model!B2 -> 118000 | D2: =Model!B2 -> 118000 | E2: =B2*(1-Assumptions!$B$3-Assumptions!$B$4)-Model!I2-Model!J2 -> 27730 | F2: =C2*(1-Assumptions!$C$3-Assumptions!$C$4)-Model!I2*(1+Assumptions!$C$5)-Model!J2 -> 18800 | G2: =D2*(1-Assumptions!$D$3-Assumptions!$D$4)-Model!I2*(1+Assumptions!$D$5)-Model!J2 -> 32410
A3: Feb-26 | B3: =Model!B3 -> 124000 | C3: =Model!B3 -> 124000 | D3: =Model!B3 -> 124000 | E3: =B3*(1-Assumptions!$B$3-Assumptions!$B$4)-Model!I3-Model!J3 -> 30340 | F3: =C3*(1-Assumptions!$C$3-Assumptions!$C$4)-Model!I3*(1+Assumptions!$C$5)-Model!J3 -> 21008 | G3: =D3*(1-Assumptions!$D$3-Assumptions!$D$4)-Model!I3*(1+Assumptions!$D$5)-Model!J3 -> 35284
A4: Mar-26 | B4: =Model!B4 -> 132000 | C4: =Model!B4 -> 132000 | D4: =Model!B4 -> 132000 | E4: =B4*(1-Assumptions!$B$3-Assumptions!$B$4)-Model!I4-Model!J4 -> 33820 | F4: =C4*(1-Assumptions!$C$3-Assumptions!$C$4)-Model!I4*(1+Assumptions!$C$5)-Model!J4 -> 23950 | G4: =D4*(1-Assumptions!$D$3-Assumptions!$D$4)-Model!I4*(1+Assumptions!$D$5)-Model!J4 -> 39115
A5: Apr-26 | B5: =Model!B5 -> 128000 | C5: =Model!B5 -> 128000 | D5: =Model!B5 -> 128000 | E5: =B5*(1-Assumptions!$B$3-Assumptions!$B$4)-Model!I5-Model!J5 -> 31480 | F5: =C5*(1-Assumptions!$C$3-Assumptions!$C$4)-Model!I5*(1+Assumptions!$C$5)-Model!J5 -> 21852 | G5: =D5*(1-Assumptions!$D$3-Assumptions!$D$4)-Model!I5*(1+Assumptions!$D$5)-Model!J5 -> 36586
A6: May-26 | B6: =Model!B6 -> 141000 | C6: =Model!B6 -> 141000 | D6: =Model!B6 -> 141000 | E6: =B6*(1-Assumptions!$B$3-Assumptions!$B$4)-Model!I6-Model!J6 -> 37385 | F6: =C6*(1-Assumptions!$C$3-Assumptions!$C$4)-Model!I6*(1+Assumptions!$C$5)-Model!J6 -> 26900 | G6: =D6*(1-Assumptions!$D$3-Assumptions!$D$4)-Model!I6*(1+Assumptions!$D$5)-Model!J6 -> 43070
A7: Jun-26 | B7: =Model!B7 -> 149000 | C7: =Model!B7 -> 149000 | D7: =Model!B7 -> 149000 | E7: =B7*(1-Assumptions!$B$3-Assumptions!$B$4)-Model!I7-Model!J7 -> 40565 | F7: =C7*(1-Assumptions!$C$3-Assumptions!$C$4)-Model!I7*(1+Assumptions!$C$5)-Model!J7 -> 29530 | G7: =D7*(1-Assumptions!$D$3-Assumptions!$D$4)-Model!I7*(1+Assumptions!$D$5)-Model!J7 -> 46595
A8: Jul-26 | B8: =Model!B8 -> 155000 | C8: =B8*(1+Assumptions!$C$2) -> 159650 | D8: =B8*(1+Assumptions!$D$2) -> 172050 | E8: =B8*(1-Assumptions!$B$3-Assumptions!$B$4)-Model!I8-Model!J8 -> 42775 | F8: =C8*(1-Assumptions!$C$3-Assumptions!$C$4)-Model!I8*(1+Assumptions!$C$5)-Model!J8 -> 33273 | G8: =D8*(1-Assumptions!$D$3-Assumptions!$D$4)-Model!I8*(1+Assumptions!$D$5)-Model!J8 -> 58096.5
A9: Aug-26 | B9: =Model!B9 -> 162000 | C9: =B9*(1+Assumptions!$C$2) -> 166860 | D9: =B9*(1+Assumptions!$D$2) -> 179820 | E9: =B9*(1-Assumptions!$B$3-Assumptions!$B$4)-Model!I9-Model!J9 -> 45470 | F9: =C9*(1-Assumptions!$C$3-Assumptions!$C$4)-Model!I9*(1+Assumptions!$C$5)-Model!J9 -> 35571.2 | G9: =D9*(1-Assumptions!$D$3-Assumptions!$D$4)-Model!I9*(1+Assumptions!$D$5)-Model!J9 -> 61499.6
A10: Sep-26 | B10: =Model!B10 -> 170000 | C10: =B10*(1+Assumptions!$C$2) -> 175100 | D10: =B10*(1+Assumptions!$D$2) -> 188700 | E10: =B10*(1-Assumptions!$B$3-Assumptions!$B$4)-Model!I10-Model!J10 -> 48650 | F10: =C10*(1-Assumptions!$C$3-Assumptions!$C$4)-Model!I10*(1+Assumptions!$C$5)-Model!J10 -> 38302 | G10: =D10*(1-Assumptions!$D$3-Assumptions!$D$4)-Model!I10*(1+Assumptions!$D$5)-Model!J10 -> 65491
A11: Oct-26 | B11: =Model!B11 -> 178000 | C11: =B11*(1+Assumptions!$C$2) -> 183340 | D11: =B11*(1+Assumptions!$D$2) -> 197580 | E11: =B11*(1-Assumptions!$B$3-Assumptions!$B$4)-Model!I11-Model!J11 -> 51830 | F11: =C11*(1-Assumptions!$C$3-Assumptions!$C$4)-Model!I11*(1+Assumptions!$C$5)-Model!J11 -> 41032.8 | G11: =D11*(1-Assumptions!$D$3-Assumptions!$D$4)-Model!I11*(1+Assumptions!$D$5)-Model!J11 -> 69482.4
A12: Nov-26 | B12: =Model!B12 -> 187000 | C12: =B12*(1+Assumptions!$C$2) -> 192610 | D12: =B12*(1+Assumptions!$D$2) -> 207570 | E12: =B12*(1-Assumptions!$B$3-Assumptions!$B$4)-Model!I12-Model!J12 -> 55495 | F12: =C12*(1-Assumptions!$C$3-Assumptions!$C$4)-Model!I12*(1+Assumptions!$C$5)-Model!J12 -> 44196.2 | G12: =D12*(1-Assumptions!$D$3-Assumptions!$D$4)-Model!I12*(1+Assumptions!$D$5)-Model!J12 -> 74062.1
A13: Dec-26 | B13: =Model!B13 -> 196000 | C13: =B13*(1+Assumptions!$C$2) -> 201880 | D13: =B13*(1+Assumptions!$D$2) -> 217560 | E13: =B13*(1-Assumptions!$B$3-Assumptions!$B$4)-Model!I13-Model!J13 -> 59160 | F13: =C13*(1-Assumptions!$C$3-Assumptions!$C$4)-Model!I13*(1+Assumptions!$C$5)-Model!J13 -> 47359.6 | G13: =D13*(1-Assumptions!$D$3-Assumptions!$D$4)-Model!I13*(1+Assumptions!$D$5)-Model!J13 -> 78641.8
